fastapi_audit_log/__init__.py
fastapi_audit_log/cleanup.py
fastapi_audit_log/config.py
fastapi_audit_log/db.py
fastapi_audit_log/logger.py
fastapi_audit_log/middleware.py
fastapi_audit_log/models.py
fastapi_audit_log-1.4.0.dist-info/licenses/LICENSE
fastapi_audit_log-1.4.0.dist-info/METADATA
fastapi_audit_log-1.4.0.dist-info/WHEEL
fastapi_audit_log-1.4.0.dist-info/top_level.txt
fastapi_audit_log-1.4.0.dist-info/RECORD
