Metadata-Version: 2.4
Name: fastapi-audit-log
Version: 1.4.0
Summary: Audit logging middleware for FastAPI apps
Author-email: Nithishraj T <nithishrajt.dev@gmail.com>
License: MIT
Keywords: fastapi,audit,logging,middleware
Classifier: Programming Language :: Python :: 3
Classifier: Framework :: FastAPI
Classifier: License :: OSI Approved :: MIT License
Requires-Python: >=3.9
License-File: LICENSE
Requires-Dist: fastapi>=0.100
Requires-Dist: sqlalchemy>=1.4
Requires-Dist: starlette>=0.28
Provides-Extra: mysql
Requires-Dist: pymysql>=1.0; extra == "mysql"
Provides-Extra: postgres
Requires-Dist: psycopg2-binary>=2.9; extra == "postgres"
Provides-Extra: oracle
Requires-Dist: cx_Oracle>=8.0; extra == "oracle"
Dynamic: license-file
